ai_eval/__init__.py
ai_eval/base.py
ai_eval/coach.py
ai_eval/coding_ai_eval.py
ai_eval/compat.py
ai_eval/export.py
ai_eval/llm.py
ai_eval/llm_services.py
ai_eval/multiagent.py
ai_eval/shortanswer.py
ai_eval/supported_models.py
ai_eval/tasks.py
ai_eval/utils.py
ai_eval/backends/__init__.py
ai_eval/backends/base.py
ai_eval/backends/custom.py
ai_eval/backends/factory.py
ai_eval/backends/judge0.py
ai_eval/static/README.txt
ai_eval/static/css/chatbox.css
ai_eval/static/css/coach_studio.css
ai_eval/static/css/coding_ai_eval.css
ai_eval/static/html/jsoneditor-iframe.html
ai_eval/static/html/marked-iframe.html
ai_eval/static/js/src/chatbox.js
ai_eval/static/js/src/chatbox_multi.js
ai_eval/static/js/src/coach.js
ai_eval/static/js/src/coding_ai_eval.js
ai_eval/static/js/src/export.js
ai_eval/static/js/src/multiagent.js
ai_eval/static/js/src/multiagent_edit.js
ai_eval/static/js/src/shortanswer.js
ai_eval/static/js/src/utils.js
ai_eval/templates/chatbox.html
ai_eval/templates/coach_layout.html
ai_eval/templates/coding_ai_eval.html
ai_eval/templates/export.html
ai_eval/templates/final_evaluation.html
ai_eval/templates/monaco.html
xblock_ai_eval-0.3.0.dist-info/licenses/LICENSE
xblock_ai_eval-0.3.0.dist-info/METADATA
xblock_ai_eval-0.3.0.dist-info/WHEEL
xblock_ai_eval-0.3.0.dist-info/entry_points.txt
xblock_ai_eval-0.3.0.dist-info/top_level.txt
xblock_ai_eval-0.3.0.dist-info/RECORD
