Metadata-Version: 2.4
Name: xblock-ai-eval
Version: 0.3.0
Summary: XBlocks to write short text and code entries with AI-driven evaluation
License: Apache 2.0
Requires-Python: >=3.11
License-File: LICENSE
Requires-Dist: XBlock
Requires-Dist: celery
Requires-Dist: chardet
Requires-Dist: litellm
Dynamic: license
Dynamic: license-file
Dynamic: requires-dist
Dynamic: requires-python
Dynamic: summary
